astro_package/__init__.py
astro_package/lint_it.py
astro_package/myouterfile.py
astro_package/state.json
astro_package/my_folder/__init__.py
astro_package/my_folder/city.json
astro_package/my_folder/myinnerfile.py
build/lib/astro_package/__init__.py
build/lib/astro_package/lint_it.py
build/lib/astro_package/myouterfile.py
build/lib/astro_package/my_folder/__init__.py
build/lib/astro_package/my_folder/myinnerfile.py
tests/test__myinnerfile.py
orc_package-0.0.1.0.dist-info/METADATA
orc_package-0.0.1.0.dist-info/WHEEL
orc_package-0.0.1.0.dist-info/top_level.txt
orc_package-0.0.1.0.dist-info/RECORD
